Indrajeet/__init__.py
Indrajeet/introduce.py
MyScripts/__init__.py
MyScripts/introduce.py
my_package_devilshorn/__init__.py
my_package_devilshorn/add_num.py
Indrajeet-0.2.dist-info/LICENCE
Indrajeet-0.2.dist-info/METADATA
Indrajeet-0.2.dist-info/WHEEL
Indrajeet-0.2.dist-info/top_level.txt
Indrajeet-0.2.dist-info/RECORD
