Metadata-Version: 2.1
Name: Indrajeet
Version: 0.2
Summary: My Personal Package
Home-page: https://github.com/javatechy/dokr
Author: Indrajeet Singh Yadav
Author-email: inderjityadav93@gmail.com
License: Proprietary
Classifier: Programming Language :: Python :: 3
Classifier: License :: Other/Proprietary License
Classifier: Operating System :: OS Independent
License-File: LICENCE
Requires-Dist: numpy (>=1.19.0)
